deduper-0.0.7.dist-info/DESCRIPTION.rst
deduper-0.0.7.dist-info/METADATA
deduper-0.0.7.dist-info/RECORD
deduper-0.0.7.dist-info/WHEEL
deduper-0.0.7.dist-info/entry_points.txt
deduper-0.0.7.dist-info/metadata.json
deduper-0.0.7.dist-info/top_level.txt
onefl/__init__.py
onefl/config.py
onefl/exc.py
onefl/hash_generator.py
onefl/link_generator.py
onefl/logutils.py
onefl/normalized_patient.py
onefl/partner_name.py
onefl/rules.py
onefl/version.py
onefl/models/__init__.py
onefl/models/base.py
onefl/models/crud_mixin.py
onefl/models/linkage_entity.py
onefl/models/partner_entity.py
onefl/models/rule_entity.py
onefl/utils/__init__.py
onefl/utils/db.py
onefl/utils/ui.py
run/__init__.py
run/hasher.py
run/linker.py
