Metadata-Version: 2.0
Name: deduper
Version: 0.0.7
Summary: OneFlorida De-duplication Software
Home-page: https://github.com/ufbmi/onefl-deduper
Author: Andrei Sura
Author-email: bmi-developers@ad.ufl.edu
License: MIT
Keywords: entity resolution,deduplication,record linkage
Platform: any
Classifier: Development Status :: 4 - Beta
Classifier: Environment :: Console
Classifier: Intended Audience :: Science/Research
Classifier: License :: OSI Approved :: MIT License
Classifier: Operating System :: MacOS :: MacOS X
Classifier: Operating System :: Microsoft :: Windows
Classifier: Operating System :: POSIX
Classifier: Operating System :: Unix
Classifier: Programming Language :: Python :: 3.4
Classifier: Programming Language :: Python :: 3.5
Classifier: Programming Language :: Python :: 3.6
Classifier: Topic :: Scientific/Engineering :: Medical Science Apps.
Requires-Dist: dill (==0.2.7.1)
Requires-Dist: pandas (==0.22.0)
Requires-Dist: pyodbc (==4.0.23)
Requires-Dist: setuptools-scm (==2.0.0)
Requires-Dist: SQLAlchemy (==1.2.7)
